ExcelPar/ConcatExcelFiles.py
ExcelPar/ConcatParquet.py
ExcelPar/ConcatTextFiles.py
ExcelPar/ExcelPar.py
ExcelPar/ForKIA.py
ExcelPar/JoinBKPFBSEG.py
ExcelPar/PreGL.py
ExcelPar/PreTB.py
ExcelPar/Run.py
ExcelPar/SliceAndSaveGL.py
ExcelPar/TBGLRecon.py
ExcelPar/__init__.py
ExcelPar/mod/AnalyzeAccounts.py
ExcelPar/mod/ChangeTBGL.py
ExcelPar/mod/CreateLeadReport.py
ExcelPar/mod/ImportGL.py
ExcelPar/mod/ImportTB.py
ExcelPar/mod/PostProcess.py
ExcelPar/mod/PreprocessGL.py
ExcelPar/mod/PreprocessTB.py
ExcelPar/mod/SetGlobal.py
ExcelPar/mod/SummarizeMonthlyVarAmount.py
ExcelPar/mylib/ChangeColumns.py
ExcelPar/mylib/ErrRetry.py
ExcelPar/mylib/ForSAP.py
ExcelPar/mylib/Object2String.py
ExcelPar/mylib/TimeCheck.py
ExcelPar/mylib/create_and_move_folder.py
ExcelPar/mylib/myFileDialog.py
ExcelPar/mylib/txt2df2db.py
excelpar-0.1.7.dist-info/METADATA
excelpar-0.1.7.dist-info/WHEEL
excelpar-0.1.7.dist-info/RECORD
