Metadata-Version: 2.1
Name: ExcelPar
Version: 0.1.7
Summary: Analyze by python, and create Excel PAR
Author-email: "Sgt. Park" <kinphw@naver.com>
Requires-Dist: clipboard>=0.0.4
Requires-Dist: dask[complete]>=2023.10.1
Requires-Dist: numpy>=1.26.1
Requires-Dist: openpyxl>=3.1.2
Requires-Dist: pandas>=2.1.2
Requires-Dist: pyautogui>=0.9.54
Requires-Dist: tqdm>=4.66.1
